MANIFEST.in
README.md
setup.cfg
setup.py
floodsens/__init__.py
floodsens/_dem.py
floodsens/_download.py
floodsens/_reproject.py
floodsens/_tile.py
floodsens/constants.py
floodsens/event.py
floodsens/inference.py
floodsens/logger.py
floodsens/model.py
floodsens/ndwi.py
floodsens/preprocessing.py
floodsens/project.py
floodsens/utils.py
floodsens.egg-info/PKG-INFO
floodsens.egg-info/SOURCES.txt
floodsens.egg-info/dependency_links.txt
floodsens.egg-info/requires.txt
floodsens.egg-info/top_level.txt