Metadata-Version: 1.1
Name: floodsens
Version: 0.2.1
Summary: Flood Segmentation on Sentinel-2 images based on Machine Learning Models
Home-page: https://github.com/gaffinetB/floodsens
Author: Ben Gaffinet
Author-email: ben@gaffinet.lu
License: MIT
Keywords: flood gis sentinel copernicus ai
Platform: UNKNOWN
Classifier: Development Status :: 2 - Pre-Alpha
Classifier: Topic :: Scientific/Engineering :: Artificial Intelligence
Classifier: Topic :: Scientific/Engineering :: GIS
Classifier: Intended Audience :: Science/Research
Classifier: Programming Language :: Python :: 3.8
